zipextimporter.py
_memimporter.pyd
py2exe/boot_common.py
py2exe/boot_com_servers.py
py2exe/boot_ctypes_com_server.py
py2exe/boot_service.py
py2exe/build_exe.py
py2exe/mf.py
py2exe/py2exe_util.pyd
py2exe/run.exe
py2exe/run_ctypes_dll.dll
py2exe/run_dll.dll
py2exe/run_isapi.dll
py2exe/run_w.exe
py2exe/__init__.py
py2exe/resources/StringTables.py
py2exe/resources/VersionInfo.py
py2exe/resources/__init__.py
py2exe/samples/advanced/icon.ico
py2exe/samples/advanced/MyService.py
py2exe/samples/advanced/setup.py
py2exe/samples/advanced/test_wmi.py
py2exe/samples/advanced/test_wx.py
py2exe/samples/extending/setup.py
py2exe/samples/extending/test_wx.py
py2exe/samples/pywin32/com_server/README.txt
py2exe/samples/pywin32/com_server/setup.py
py2exe/samples/pywin32/com_server/test_interp.py
py2exe/samples/pywin32/com_server/test_interp.vbs
py2exe/samples/pywin32/com_typelib/README.txt
py2exe/samples/pywin32/com_typelib/build_gen/word/docmaker.py
py2exe/samples/pywin32/com_typelib/build_gen/word/setup.py
py2exe/samples/pywin32/com_typelib/pre_gen/wscript/setup.py
py2exe/samples/pywin32/com_typelib/pre_gen/wscript/show_info.py
py2exe/samples/pywin32/com_typelib/pre_gen/wscript/wsh-typelib-stubs.py
py2exe/samples/pywin32/isapi/README.txt
py2exe/samples/pywin32/isapi/setup.py
py2exe/samples/simple/hello.py
py2exe/samples/simple/setup.py
py2exe/samples/simple/test_wx.py
py2exe/samples/singlefile/comserver/setup.py
py2exe/samples/singlefile/comserver/setup_client.py
py2exe/samples/singlefile/comserver/test.py
py2exe/samples/singlefile/gui/setup.py
py2exe/samples/singlefile/gui/test_wx.py
py2exe/samples/user_access_control/hello.py
py2exe/samples/user_access_control/README.txt
py2exe/samples/user_access_control/setup.py
py2exe_py2-0.6.9.data/scripts/py2exe_postinstall.py
py2exe_py2-0.6.9.dist-info/METADATA
py2exe_py2-0.6.9.dist-info/RECORD
py2exe_py2-0.6.9.dist-info/WHEEL
