Metadata-Version: 2.0
Name: py2exe_py2
Version: 0.6.9
Summary: Build standalone executables for Windows
Home-page: http://www.py2exe.org/
Author: Jimmy Retzlaff
Author-email: jimmy@retzlaff.com
License: MIT/X11, MPL 1.1
Download-URL: http://sourceforge.net/project/showfiles.php?group_id=15583
Platform: Windows
Classifier: Development Status :: 5 - Production/Stable
